spark_loader/__init__.py
spark_loader/config.py
spark_loader/logging.py
spark_loader/spark.py
spark_loader-0.1.0.dist-info/METADATA
spark_loader-0.1.0.dist-info/WHEEL
spark_loader-0.1.0.dist-info/RECORD
