Metadata-Version: 2.1
Name: spark-loader
Version: 0.1.0
Summary: loads spark
Author: Edward Yang
Author-email: eddiepyang@gmail.com
Requires-Python: >=3.9,<3.12
Classifier: Programming Language :: Python :: 3
Classifier: Programming Language :: Python :: 3.9
Classifier: Programming Language :: Python :: 3.10
Classifier: Programming Language :: Python :: 3.11
Requires-Dist: hydra-core (>=1.1.1,<2.0.0)
Requires-Dist: pyarrow (>=14.0.1,<15.0.0)
Requires-Dist: pyspark (>=3.5,<3.6)
Requires-Dist: python-rapidjson (>=1.13,<2.0)
Requires-Dist: spark-nlp (>=5.2.0,<6.0.0)
Requires-Dist: structlog (>=23.2.0,<24.0.0)
